slashbot.py
slashbot-0.0.2.dist-info/LICENSE
slashbot-0.0.2.dist-info/METADATA
slashbot-0.0.2.dist-info/WHEEL
slashbot-0.0.2.dist-info/top_level.txt
slashbot-0.0.2.dist-info/RECORD
