Metadata-Version: 2.1
Name: slashbot
Version: 0.0.2
Summary: A library for creating Slack slash commands.
Home-page: https://github.com/ebrassell/slashbot
Author: Eric Brassell
Author-email: ebrassell-slashbot@gmail.com
License: BSD
Project-URL: Bug Tracker, https://github.com/ebrassell/slashbot/issues
Keywords: slack bot slash slackbot lambda
Platform: UNKNOWN
Classifier: Programming Language :: Python :: 3
Classifier: License :: OSI Approved :: BSD License
Classifier: Operating System :: OS Independent
Requires-Python: >=3.6
License-File: LICENSE
Requires-Dist: requests (>=2.0.0)
